OAuthClientUser-0.3.0.dist-info/DESCRIPTION.rst
OAuthClientUser-0.3.0.dist-info/METADATA
OAuthClientUser-0.3.0.dist-info/RECORD
OAuthClientUser-0.3.0.dist-info/WHEEL
OAuthClientUser-0.3.0.dist-info/metadata.json
OAuthClientUser-0.3.0.dist-info/top_level.txt
OAuthUser/__init__.py
OAuthUser/admin.py
OAuthUser/apps.py
OAuthUser/authentication.py
OAuthUser/http_utils.py
OAuthUser/models.py
OAuthUser/permissions.py
OAuthUser/serializers.py
OAuthUser/tests.py
OAuthUser/urls.py
OAuthUser/utils.py
OAuthUser/views.py
OAuthUser/migrations/0001_initial.py
OAuthUser/migrations/0002_auto_20171116_2317.py
OAuthUser/migrations/__init__.py
