Metadata-Version: 2.0
Name: OAuthClientUser
Version: 0.3.0
Summary: A User Authenticate APP for OAuth2 of django-oauth-toolkit
Home-page: https://github.com/lixujia/OAuthClientUser
Author: Xujia Li
Author-email: lixujia.cn@gmail.com
License: MIT
Keywords: Django OAuth2 Authenticate UserData
Platform: UNKNOWN
Classifier: Development Status :: 4 - Beta
Classifier: Intended Audience :: Developers
Classifier: Topic :: Internet :: WWW/HTTP :: Session
Classifier: License :: OSI Approved :: MIT License
Classifier: Programming Language :: Python :: 2.7
Classifier: Programming Language :: Python :: 3.6
Requires-Dist: django
Requires-Dist: djangorestframework
Requires-Dist: djangorestframework-jwt
Requires-Dist: requests
Requires-Dist: cryptography
